icedata/__init__.py
icedata/datasets/__init__.py
icedata/datasets/birds/__init__.py
icedata/datasets/birds/data.py
icedata/datasets/birds/dataset.py
icedata/datasets/birds/parser.py
icedata/datasets/birds/trained_models.py
icedata/datasets/biwi/__init__.py
icedata/datasets/biwi/data.py
icedata/datasets/biwi/dataset.py
icedata/datasets/biwi/parser.py
icedata/datasets/biwi/tests/__init__.py
icedata/datasets/biwi/tests/conftest.py
icedata/datasets/biwi/tests/test_parsers.py
icedata/datasets/coco/__init__.py
icedata/datasets/coco/data.py
icedata/datasets/coco/dataset.py
icedata/datasets/coco/parser.py
icedata/datasets/coco/trained_models.py
icedata/datasets/fridge/__init__.py
icedata/datasets/fridge/data.py
icedata/datasets/fridge/dataset.py
icedata/datasets/fridge/parser.py
icedata/datasets/fridge/trained_models.py
icedata/datasets/fridge/tests/__init__.py
icedata/datasets/fridge/tests/conftest.py
icedata/datasets/fridge/tests/test_data.py
icedata/datasets/fridge/tests/test_parsers.py
icedata/datasets/fridge/tests/test_trained_models.py
icedata/datasets/ochuman/__init__.py
icedata/datasets/ochuman/data.py
icedata/datasets/ochuman/parser.py
icedata/datasets/ochuman/tests/__init__.py
icedata/datasets/ochuman/tests/conftest.py
icedata/datasets/ochuman/tests/test_parsers.py
icedata/datasets/pennfudan/__init__.py
icedata/datasets/pennfudan/data.py
icedata/datasets/pennfudan/dataset.py
icedata/datasets/pennfudan/parser.py
icedata/datasets/pennfudan/trained_models.py
icedata/datasets/pennfudan/tests/__init__.py
icedata/datasets/pennfudan/tests/conftest.py
icedata/datasets/pennfudan/tests/test_parsers.py
icedata/datasets/pennfudan/tests/test_trained_models.py
icedata/datasets/pets/__init__.py
icedata/datasets/pets/data.py
icedata/datasets/pets/dataset.py
icedata/datasets/pets/parser.py
icedata/datasets/pets/trained_models.py
icedata/datasets/pets/tests/__init__.py
icedata/datasets/pets/tests/conftest.py
icedata/datasets/pets/tests/test_data.py
icedata-0.5.1.dist-info/LICENSE
icedata-0.5.1.dist-info/METADATA
icedata-0.5.1.dist-info/WHEEL
icedata-0.5.1.dist-info/top_level.txt
icedata-0.5.1.dist-info/RECORD
